tiny_retriever/__init__.py
tiny_retriever/exceptions.py
tiny_retriever/tiny_retriever.py
tiny_retriever/tiny_retriever.pyi
tiny_retriever-0.2.0.dist-info/METADATA
tiny_retriever-0.2.0.dist-info/WHEEL
tiny_retriever-0.2.0.dist-info/licenses/AUTHORS.md
tiny_retriever-0.2.0.dist-info/licenses/LICENSE
tiny_retriever-0.2.0.dist-info/RECORD
