Metadata-Version: 2.4
Name: tiny-retriever
Version: 0.2.0
Summary: A synchronous wrapper for AIOHTTP
Project-URL: Changelog, https://tiny-retriever.readthedocs.io/en/latest/CHANGELOG
Project-URL: CI, https://github.com/cheginit/tiny-retriever/actions
Project-URL: Homepage, https://tiny-retriever.readthedocs.io
Project-URL: Issues, https://github.com/cheginit/tiny-retriever/issues
Author-email: Taher Chegini <cheginit@gmail.com>
License: MIT
License-File: AUTHORS.md
License-File: LICENSE
Classifier: Development Status :: 4 - Beta
Classifier: Intended Audience :: Science/Research
Classifier: License :: OSI Approved :: MIT License
Classifier: Operating System :: OS Independent
Classifier: Programming Language :: Python
Classifier: Programming Language :: Python :: 3 :: Only
Classifier: Programming Language :: Python :: 3.10
Classifier: Programming Language :: Python :: 3.11
Classifier: Programming Language :: Python :: 3.12
Classifier: Programming Language :: Python :: 3.13
Classifier: Programming Language :: Python :: 3.14
Classifier: Topic :: Scientific/Engineering
Classifier: Topic :: Scientific/Engineering :: GIS
Classifier: Typing :: Typed
Requires-Python: >=3.10
Requires-Dist: aiofiles
Requires-Dist: aiohttp>=3.8.6
Provides-Extra: dev
Requires-Dist: aioresponses; extra == 'dev'
Requires-Dist: geopandas>=1; extra == 'dev'
Requires-Dist: ipykernel; extra == 'dev'
Requires-Dist: ipywidgets; extra == 'dev'
Requires-Dist: mapclassify; extra == 'dev'
Requires-Dist: matplotlib; extra == 'dev'
Requires-Dist: numpy>=2; extra == 'dev'
Requires-Dist: orjson; extra == 'dev'
Requires-Dist: pytest; extra == 'dev'
Requires-Dist: pytest-aiohttp; extra == 'dev'
Requires-Dist: pytest-asyncio; extra == 'dev'
Requires-Dist: rioxarray; extra == 'dev'
Requires-Dist: shapely>=2; extra == 'dev'
Provides-Extra: docs
Requires-Dist: black; extra == 'docs'
Requires-Dist: mkdocs; extra == 'docs'
Requires-Dist: mkdocs-jupyter; extra == 'docs'
Requires-Dist: mkdocs-material[imaging,recommended]; extra == 'docs'
Requires-Dist: mkdocstrings-python; extra == 'docs'
Provides-Extra: lint
Requires-Dist: codespell; extra == 'lint'
Requires-Dist: pre-commit; extra == 'lint'
Provides-Extra: test
Requires-Dist: aioresponses; extra == 'test'
Requires-Dist: coverage[toml]; extra == 'test'
Requires-Dist: orjson; extra == 'test'
Requires-Dist: pytest-cov; extra == 'test'
Requires-Dist: pytest-sugar; extra == 'test'
Requires-Dist: shapely>=2; extra == 'test'
Provides-Extra: typecheck
Requires-Dist: pyright; extra == 'typecheck'
